LICENSE
README.md
setup.py
maixtool/__init__.py
maixtool/__main__.py
maixtool/app_deploy.py
maixtool/app_release.py
maixtool/i18n.py
maixtool/maixcdk.py
maixtool/maixtool.py
maixtool/version.py
maixtool.egg-info/PKG-INFO
maixtool.egg-info/SOURCES.txt
maixtool.egg-info/dependency_links.txt
maixtool.egg-info/entry_points.txt
maixtool.egg-info/requires.txt
maixtool.egg-info/top_level.txt